auto_quarot/__init__.py
auto_quarot/hadamard_utils.py
auto_quarot/utils.py
auto_quarot-0.1.0.dist-info/LICENSE
auto_quarot-0.1.0.dist-info/METADATA
auto_quarot-0.1.0.dist-info/WHEEL
auto_quarot-0.1.0.dist-info/top_level.txt
auto_quarot-0.1.0.dist-info/RECORD
