Metadata-Version: 2.1
Name: auto_quarot
Version: 0.1.0
Summary: Auto convert transformers models to QuaRot
Author: sgsdxzy
License: Apache 2.0
License-File: LICENSE
Requires-Dist: torch
Requires-Dist: transformers
Requires-Dist: fast-hadamard-transform
Requires-Dist: tqdm
